snapshot_query/__init__.py
snapshot_query/__main__.py
snapshot_query/cli.py
snapshot_query/mcp_server.py
snapshot_query/models.py
snapshot_query/query.py
snapshot_query-0.1.3.dist-info/METADATA
snapshot_query-0.1.3.dist-info/WHEEL
snapshot_query-0.1.3.dist-info/entry_points.txt
snapshot_query-0.1.3.dist-info/licenses/LICENSE
snapshot_query-0.1.3.dist-info/RECORD
