Metadata-Version: 2.4
Name: snapshot-query
Version: 0.1.3
Summary: Efficiently query and analyze snapshot log files generated by cursor-ide-browser
Project-URL: Homepage, https://github.com/cursor-ide/snapshot-query
Project-URL: Documentation, https://github.com/cursor-ide/snapshot-query#readme
Project-URL: Repository, https://github.com/cursor-ide/snapshot-query
Author-email: Cursor IDE Team <support@cursor.com>
License: MIT
License-File: LICENSE
Keywords: accessibility,browser,cursor,mcp,pydantic,query,snapshot
Classifier: Development Status :: 4 - Beta
Classifier: Intended Audience :: Developers
Classifier: License :: OSI Approved :: MIT License
Classifier: Programming Language :: Python :: 3
Classifier: Programming Language :: Python :: 3.8
Classifier: Programming Language :: Python :: 3.9
Classifier: Programming Language :: Python :: 3.10
Classifier: Programming Language :: Python :: 3.11
Classifier: Programming Language :: Python :: 3.12
Requires-Python: >=3.8
Requires-Dist: mcp>=1.0.0
Requires-Dist: pydantic>=2.0.0
Requires-Dist: pyyaml>=6.0
Provides-Extra: dev
Requires-Dist: pytest-cov>=4.0.0; extra == 'dev'
Requires-Dist: pytest>=7.0.0; extra == 'dev'
